naturalcolors/__init__.py
naturalcolors/colormaps.json
naturalcolors/colorpalette.py
naturalcolors-1.0.5.dist-info/LICENSE
naturalcolors-1.0.5.dist-info/METADATA
naturalcolors-1.0.5.dist-info/WHEEL
naturalcolors-1.0.5.dist-info/top_level.txt
naturalcolors-1.0.5.dist-info/RECORD
